minchin.pelican.plugins.image_process-1.2.1-py3.9-nspkg.pth
minchin/pelican/plugins/image_process.py
tests/__init__.py
tests/test_image_process.py
tests/test_data/pelican-bird.jpg
tests/test_data/pelican-bird.png
tests/test_data/results/blur/pelican-bird.jpg
tests/test_data/results/blur/pelican-bird.png
tests/test_data/results/contour/pelican-bird.jpg
tests/test_data/results/contour/pelican-bird.png
tests/test_data/results/crop/pelican-bird.jpg
tests/test_data/results/crop/pelican-bird.png
tests/test_data/results/detail/pelican-bird.jpg
tests/test_data/results/detail/pelican-bird.png
tests/test_data/results/edge_enhance/pelican-bird.jpg
tests/test_data/results/edge_enhance/pelican-bird.png
tests/test_data/results/edge_enhance_more/pelican-bird.jpg
tests/test_data/results/edge_enhance_more/pelican-bird.png
tests/test_data/results/emboss/pelican-bird.jpg
tests/test_data/results/emboss/pelican-bird.png
tests/test_data/results/find_edges/pelican-bird.jpg
tests/test_data/results/find_edges/pelican-bird.png
tests/test_data/results/flip_horizontal/pelican-bird.jpg
tests/test_data/results/flip_horizontal/pelican-bird.png
tests/test_data/results/flip_vertical/pelican-bird.jpg
tests/test_data/results/flip_vertical/pelican-bird.png
tests/test_data/results/grayscale/pelican-bird.jpg
tests/test_data/results/grayscale/pelican-bird.png
tests/test_data/results/resize/pelican-bird.jpg
tests/test_data/results/resize/pelican-bird.png
tests/test_data/results/rotate/pelican-bird.jpg
tests/test_data/results/rotate/pelican-bird.png
tests/test_data/results/scale_in/pelican-bird.jpg
tests/test_data/results/scale_in/pelican-bird.png
tests/test_data/results/scale_out/pelican-bird.jpg
tests/test_data/results/scale_out/pelican-bird.png
tests/test_data/results/sharpen/pelican-bird.jpg
tests/test_data/results/sharpen/pelican-bird.png
tests/test_data/results/smooth/pelican-bird.jpg
tests/test_data/results/smooth/pelican-bird.png
tests/test_data/results/smooth_more/pelican-bird.jpg
minchin.pelican.plugins.image_process-1.2.1.dist-info/LICENSE
minchin.pelican.plugins.image_process-1.2.1.dist-info/METADATA
minchin.pelican.plugins.image_process-1.2.1.dist-info/WHEEL
minchin.pelican.plugins.image_process-1.2.1.dist-info/namespace_packages.txt
minchin.pelican.plugins.image_process-1.2.1.dist-info/top_level.txt
minchin.pelican.plugins.image_process-1.2.1.dist-info/RECORD
