Metadata-Version: 2.1
Name: minchin.pelican.plugins.image-process
Version: 1.2.1
Summary: Pelican plugin for automating image processing. Written in Python.
Home-page: https://github.com/MinchinWeb/minchin.pelican.plugins.image_process
Author: William Minchin
Author-email: w_minchin@hotmail.com
License: Affero GPL v3
Platform: any
Classifier: Framework :: Pelican :: Plugins
Classifier: Development Status :: 7 - Inactive
Classifier: Programming Language :: Python :: 3
Classifier: Programming Language :: Python :: 3.4
Classifier: Programming Language :: Python :: 3.5
Classifier: Programming Language :: Python :: 3.6
Classifier: Programming Language :: Python :: 3.7
Classifier: Programming Language :: Python :: 3.8
Classifier: Programming Language :: Python :: 3.9
Classifier: Natural Language :: English
Classifier: Environment :: Console
Classifier: Environment :: Web Environment
Classifier: Intended Audience :: Developers
Classifier: Operating System :: OS Independent
Classifier: License :: OSI Approved :: GNU Affero General Public License v3
Classifier: Topic :: Software Development :: Libraries :: Python Modules
Classifier: Topic :: Multimedia :: Graphics
Requires-Dist: beautifulsoup4
Requires-Dist: pelican
Requires-Dist: pillow
Requires-Dist: six
Provides-Extra: all
Requires-Dist: pip ; extra == 'all'
Requires-Dist: wheel ; extra == 'all'
Requires-Dist: setuptools (>=18.0) ; extra == 'all'
Requires-Dist: twine ; extra == 'all'
Requires-Dist: pip-tools ; extra == 'all'
Requires-Dist: minchin.releaser ; extra == 'all'
Requires-Dist: pycodestyle ; extra == 'all'
Requires-Dist: mock ; extra == 'all'
Provides-Extra: build
Requires-Dist: pip ; extra == 'build'
Requires-Dist: wheel ; extra == 'build'
Requires-Dist: setuptools (>=18.0) ; extra == 'build'
Requires-Dist: twine ; extra == 'build'
Requires-Dist: pip-tools ; extra == 'build'
Requires-Dist: minchin.releaser ; extra == 'build'
Provides-Extra: dev
Requires-Dist: pycodestyle ; extra == 'dev'
Provides-Extra: test
Requires-Dist: mock ; extra == 'test'
